{
  "cn": {
    "title": "关于进行 Ethereum Classic（ETC）节点升级的公告",
    "data": "2021-09-04",
    "id": 129,
    "watch": 396,
    "message": [
      {
        "type": 0,
        "data": "亲爱的派友："
      },
      {
        "type": 0,
        "data": "比特派正在对 Ethereum Classic（ETC）节点进行升级 ，为保障您的资产安全，当前已暂停 ETC 收发、云钱包充提等业务。"
      },
      {
        "type": 0,
        "data": "相关服务将在升级稳定后第一时间恢复。"
      },
      {
        "type": 0,
        "data": "感谢您对比特派 Bitpie 的支持。"
      },
      {
        "type": 0,
        "data": "比特派团队<br/>2021/09/04"
      }
    ]
  }
}